jinja_script_block/__init__.py
jinja_script_block-0.0.4.dist-info/METADATA
jinja_script_block-0.0.4.dist-info/WHEEL
jinja_script_block-0.0.4.dist-info/top_level.txt
jinja_script_block-0.0.4.dist-info/RECORD
