Metadata-Version: 2.1
Name: jinja-script-block
Version: 0.0.4
Home-page: https://github.com/jinrudals/jinja2_script.git
Author: Benjamin Jin
Author-email: jinrudals135@naver.com
License: BSD
Requires-Dist: Jinja2
